tinybird/__cli__.py
tinybird/check_pypi.py
tinybird/client.py
tinybird/config.py
tinybird/connectors.py
tinybird/context.py
tinybird/datafile_common.py
tinybird/datatypes.py
tinybird/feedback_manager.py
tinybird/git_settings.py
tinybird/sql.py
tinybird/sql_template.py
tinybird/sql_template_fmt.py
tinybird/sql_toolset.py
tinybird/syncasync.py
tinybird/tb_cli.py
tinybird/tornado_template.py
tinybird/ch_utils/constants.py
tinybird/ch_utils/engine.py
tinybird/tb_cli_modules/auth.py
tinybird/tb_cli_modules/branch.py
tinybird/tb_cli_modules/cicd.py
tinybird/tb_cli_modules/cli.py
tinybird/tb_cli_modules/common.py
tinybird/tb_cli_modules/config.py
tinybird/tb_cli_modules/connection.py
tinybird/tb_cli_modules/datasource.py
tinybird/tb_cli_modules/exceptions.py
tinybird/tb_cli_modules/fmt.py
tinybird/tb_cli_modules/job.py
tinybird/tb_cli_modules/pipe.py
tinybird/tb_cli_modules/regions.py
tinybird/tb_cli_modules/tag.py
tinybird/tb_cli_modules/telemetry.py
tinybird/tb_cli_modules/test.py
tinybird/tb_cli_modules/token.py
tinybird/tb_cli_modules/workspace.py
tinybird/tb_cli_modules/workspace_members.py
tinybird/tb_cli_modules/tinyunit/tinyunit.py
tinybird/tb_cli_modules/tinyunit/tinyunit_lib.py
tinybird_cli-5.21.1.dist-info/METADATA
tinybird_cli-5.21.1.dist-info/WHEEL
tinybird_cli-5.21.1.dist-info/entry_points.txt
tinybird_cli-5.21.1.dist-info/top_level.txt
tinybird_cli-5.21.1.dist-info/RECORD
