Metadata-Version: 2.2
Name: tinybird_cli
Version: 5.21.1
Summary: Tinybird Command Line Tool
Home-page: https://www.tinybird.co/docs/cli
Author: Tinybird
Author-email: support@tinybird.co
Requires-Python: >=3.9, <3.14
Requires-Dist: aiofiles==24.1.0
Requires-Dist: clickhouse-toolset==0.34.dev0
Requires-Dist: click<8.2,>=8.1.8
Requires-Dist: colorama==0.4.6
Requires-Dist: cryptography~=41.0.0
Requires-Dist: croniter==1.3.15
Requires-Dist: GitPython~=3.1.32
Requires-Dist: humanfriendly~=8.2
Requires-Dist: pydantic~=2.8.0
Requires-Dist: pyperclip==1.8.2
Requires-Dist: pyyaml<6.1,>=6.0
Requires-Dist: requests<3,>=2.28.1
Requires-Dist: shandy-sqlfmt==0.11.1
Requires-Dist: shandy-sqlfmt[jinjafmt]==0.11.1
Requires-Dist: toposort==1.10
Requires-Dist: tornado~=6.0.0
Requires-Dist: urllib3<2,>=1.26.14
Requires-Dist: wheel
Requires-Dist: packaging<24,>=23.1
Provides-Extra: bigquery
Requires-Dist: gsutil==4.58; extra == "bigquery"
Requires-Dist: google-api-python-client==2.0.2; extra == "bigquery"
Requires-Dist: google-auth==1.27.1; extra == "bigquery"
Requires-Dist: google-auth-httplib2==0.1.0; extra == "bigquery"
Requires-Dist: google-cloud-storage==2.4.0; extra == "bigquery"
Requires-Dist: google-cloud-bigquery==2.11.0; extra == "bigquery"
Provides-Extra: snowflake
Requires-Dist: snowflake-connector-python~=3.12.3; extra == "snowflake"
Requires-Dist: gsutil==4.58; extra == "snowflake"
Requires-Dist: google-api-python-client==2.0.2; extra == "snowflake"
Requires-Dist: google-auth==1.27.1; extra == "snowflake"
Requires-Dist: google-auth-httplib2==0.1.0; extra == "snowflake"
Requires-Dist: google-cloud-storage==2.4.0; extra == "snowflake"
Requires-Dist: oauth2client==3.0.0; extra == "snowflake"
Requires-Dist: chardet<4,>=3.0.2; extra == "snowflake"
Requires-Dist: pyOpenSSL<20.0.0,>=16.2.0; extra == "snowflake"
Dynamic: author
Dynamic: author-email
Dynamic: description
Dynamic: description-content-type
Dynamic: home-page
Dynamic: provides-extra
Dynamic: requires-dist
Dynamic: requires-python
Dynamic: summary
